{"expert_traj": [{"action": "look", "observation": "You are in the middle of a room. Looking quickly around you, you see nothing."}, {"action": "go to toaster 1", "observation": "You arrive at loc 22. On the toaster 1, you see nothing."}, {"action": "go to stoveburner 1", "observation": "You arrive at loc 14. On the stoveburner 1, you see a pot 1."}, {"action": "go to stoveburner 2", "observation": "You arrive at loc 18. On the stoveburner 2, you see a pan 1."}, {"action": "take pan 1 from stoveburner 2", "observation": "You pick up the pan 1 from the stoveburner 2."}, {"action": "go to sinkbasin 1", "observation": "You arrive at loc 29. On the sinkbasin 1, you see nothing."}, {"action": "clean pan 1 with sinkbasin 1", "observation": "You clean the pan 1 using the sinkbasin 1."}, {"action": "go to countertop 1", "observation": "You arrive at loc 11. On the countertop 1, you see nothing."}, {"action": "put pan 1 in/on countertop 1", "observation": "You put the pan 1 in/on the countertop 1."}], "env_name": 9, "gamefile": ["/storage/ukp/work/fang/alfworld/alfworld/data/alfworld/json_2.1.1/valid_unseen/pick_clean_then_place_in_recep-Pan-None-CounterTop-10/trial_T20190908_032518_891433/game.tw-pddl"]}